{
  "单据编号": "100294",
  "业务类型": "差旅费报销",
  "公司": "中财汇通控股有限公司",
  "部门": "行政管理部",
  "报销人": "谢雅琳",
  "出差类型": "参加培训",
  "出发地": "北京",
  "目的地": "广州",
  "途径城市": "无",
  "出差时间": "2026.5.22-2026.5.24",
  "费用分摊主体1": "行政管理部",
  "费用分摊主体2": "区块链事业部",
  "行程明细": [
    {
      "行程类型": "飞机",
      "出发日期": "2026.5.22",
      "到达日期": "2026.5.22",
      "出发地": "北京",
      "到达地": "广州",
      "交通工具": "飞机",
      "座位等级": "经济舱",
      "时间": "16:33-17:51",
      "票价": "1894.00",
      "燃油附加费": "150.00",
      "增值税税率": "9%",
      "增值税税额": "192.06",
      "民航发展基金": "50.00",
      "其他税费": "40.00",
      "合计": "2134.00",
      "电子客票号": "3808348378865",
      "保险费": "30.00",
      "开票状态": "已开票",
      "发票号码": "CA9817231092577",
      "旅客": "谢雅琳",
      "购买方": "中财汇通控股有限公司",
      "出发": "北京首都国际机场",
      "到达": "广州白云国际机场",
      "线下预订审批描述": "",
      "实际支付金额": "2134.00"
    },
    {
      "行程类型": "其他",
      "出发日期": "2026.5.23",
      "到达日期": "2026.5.23",
      "出发地": "广州",
      "到达地": "广州",
      "交通工具": "出租车/汽车/地铁",
      "发票类型": "增值税普通电子发票",
      "购买方名称": "中财汇通控股有限公司",
      "购买方统一社会信用代码/纳税人识别号": "91110000MA1234567X",
      "销售方名称": "广州白云出租车集团有限公司",
      "销售方统一社会信用代码/纳税人识别号": "91440101MA0034567C",
      "发票号码": "DT3542349627170",
      "开票日期": "2026.5.23",
      "价税合计": "30.49",
      "税率": "3%",
      "税额": "0.89",
      "不含税金额": "29.60",
      "税目": "运输服务",
      "行程单ID": "DT20260523001",
      "行程金额": "30.49",
      "车型": "出租车",
      "行程人手机号": "13838330009",
      "行程时间": "2026-05-23 11:24至2026-05-23 11:42",
      "城市": "广州",
      "起点": "广州白云国际机场",
      "终点": "广州市海珠区琶洲大道东88号"
    },
    {
      "行程类型": "其他",
      "出发日期": "2026.5.24",
      "到达日期": "2026.5.24",
      "出发地": "广州",
      "到达地": "广州",
      "交通工具": "出租车/汽车/地铁",
      "发票类型": "增值税普通电子发票",
      "购买方名称": "中财汇通控股有限公司",
      "购买方统一社会信用代码/纳税人识别号": "91110000MA1234567X",
      "销售方名称": "广州白云出租车集团有限公司",
      "销售方统一社会信用代码/纳税人识别号": "91440101MA0034567C",
      "发票号码": "DT6858367814509",
      "开票日期": "2026.5.24",
      "价税合计": "57.52",
      "税率": "3%",
      "税额": "1.68",
      "不含税金额": "55.84",
      "税目": "运输服务",
      "行程单ID": "DT20260524002",
      "行程金额": "57.52",
      "车型": "网约车",
      "行程人手机号": "13833057633",
      "行程时间": "2026-05-24 20:51至2026-05-24 21:18",
      "城市": "广州",
      "起点": "广州市越秀区东风中路362号珠江颐德大厦",
      "终点": "广州市天河区林和西横路215号"
    },
    {
      "行程类型": "飞机",
      "出发日期": "2026.5.24",
      "到达日期": "2026.5.24",
      "出发地": "广州",
      "到达地": "北京",
      "交通工具": "飞机",
      "座位等级": "经济舱",
      "时间": "14:47-17:25",
      "票价": "2583.00",
      "燃油附加费": "120.00",
      "增值税税率": "9%",
      "增值税税额": "247.77",
      "民航发展基金": "50.00",
      "其他税费": "0.00",
      "合计": "2753.00",
      "电子客票号": "5491467078799",
      "保险费": "30.00",
      "开票状态": "已开票",
      "发票号码": "CA9356254770600",
      "旅客": "谢雅琳",
      "购买方": "中财汇通控股有限公司",
      "出发": "广州白云国际机场",
      "到达": "北京首都国际机场",
      "线下预订审批描述": "",
      "实际支付金额": "2753.00"
    }
  ],
  "住宿明细": [
    {
      "入住日期": "2026.5.22",
      "退房日期": "2026.5.24",
      "酒店名称": "广州科学城翡翠希尔顿酒店",
      "所在位置": "广州市黄埔区科学城凝彩路28号",
      "住宿单价": "550.00",
      "住宿总额": "1100.00",
      "住宿人": "谢雅琳",
      "发票类型": "增值税专用电子发票",
      "购买方名称": "中财汇通控股有限公司",
      "购买方统一社会信用代码/纳税人识别号": "91110000MA1234567X",
      "销售方名称": "广州科学城翡翠希尔顿酒店有限公司",
      "销售方统一社会信用代码/纳税人识别号": "9144030084360083A",
      "发票号码": "XS9584936704710",
      "开票日期": "2026.5.24",
      "价税合计": "1100.00",
      "税额": "62.26",
      "税率": "6%",
      "不含税金额": "1037.74",
      "税目": "住宿服务",
      "线下预订审批描述": "",
      "实际支付金额": "1100.00"
    }
  ],
  "费用分摊明细": [
    {
      "费用分摊主体": "行政管理部",
      "分摊比例": "50%",
      "报销金额": "3037.51"
    },
    {
      "费用分摊主体": "区块链事业部",
      "分摊比例": "50%",
      "报销金额": "3037.50"
    }
  ],
  "资金支付信息": {
    "付款方式": "对私支付",
    "支付金额": "6075.01",
    "对私支付": "谢雅琳",
    "对公支付": ""
  }
}