{
  "单据编号": "100875",
  "业务类型": "差旅费报销",
  "公司": "中财汇通科技股份有限公司",
  "部门": "产品管理部",
  "报销人": "梁梓涵",
  "出差类型": "公务出差",
  "出发地": "上海",
  "目的地": "西安",
  "途径城市": "无",
  "出差时间": "2026.9.14-2026.9.19",
  "费用分摊主体1": "产品管理部",
  "费用分摊主体2": "客户运营部",
  "行程明细": [
    {
      "行程类型": "飞机",
      "出发日期": "2026.9.14",
      "到达日期": "2026.9.14",
      "出发地": "上海",
      "到达地": "西安",
      "交通工具": "飞机",
      "座位等级": "经济舱",
      "时间": "08:07-11:03",
      "票价": "1690.00",
      "燃油附加费": "50.00",
      "增值税税率": "9%",
      "增值税税额": "164.70",
      "民航发展基金": "50.00",
      "其他税费": "40.00",
      "合计": "1830.00",
      "电子客票号": "1487897340649",
      "保险费": "30.00",
      "开票状态": "已开票",
      "发票号码": "CA8990249712361",
      "旅客": "梁梓涵",
      "购买方": "中财汇通科技股份有限公司",
      "出发": "上海虹桥国际机场",
      "到达": "西安咸阳国际机场",
      "线下预订审批描述": "",
      "实际支付金额": "1830.00"
    },
    {
      "行程类型": "其他",
      "出发日期": "2026.9.14",
      "到达日期": "2026.9.14",
      "出发地": "西安",
      "到达地": "西安",
      "交通工具": "出租车/汽车/地铁",
      "发票类型": "增值税普通电子发票",
      "购买方名称": "中财汇通科技股份有限公司",
      "购买方统一社会信用代码/纳税人识别号": "91110000MA2234567Y",
      "销售方名称": "西安前进出租车有限公司",
      "销售方统一社会信用代码/纳税人识别号": "91610100MA0089012H",
      "发票号码": "DT6583501574029",
      "开票日期": "2026.9.14",
      "价税合计": "51.31",
      "税率": "3%",
      "税额": "1.49",
      "不含税金额": "49.82",
      "税目": "运输服务",
      "行程单ID": "DT20260914000",
      "行程金额": "51.31",
      "车型": "出租车",
      "行程人手机号": "13822020505",
      "行程时间": "2026-09-14 17:41至2026-09-14 18:05",
      "城市": "西安",
      "起点": "西安市雁塔区唐延路11号禾盛京广中心",
      "终点": "西安北站"
    },
    {
      "行程类型": "其他",
      "出发日期": "2026.9.16",
      "到达日期": "2026.9.16",
      "出发地": "西安",
      "到达地": "西安",
      "交通工具": "出租车/汽车/地铁",
      "发票类型": "增值税普通电子发票",
      "购买方名称": "中财汇通科技股份有限公司",
      "购买方统一社会信用代码/纳税人识别号": "91110000MA2234567Y",
      "销售方名称": "西安前进出租车有限公司",
      "销售方统一社会信用代码/纳税人识别号": "91610100MA0089012H",
      "发票号码": "DT7724634202356",
      "开票日期": "2026.9.16",
      "价税合计": "33.65",
      "税率": "3%",
      "税额": "0.98",
      "不含税金额": "32.67",
      "税目": "运输服务",
      "行程单ID": "DT20260916002",
      "行程金额": "33.65",
      "车型": "网约车",
      "行程人手机号": "13871063761",
      "行程时间": "2026-09-16 20:05至2026-09-16 20:51",
      "城市": "西安",
      "起点": "西安市高新区沣惠南路34号",
      "终点": "西安咸阳国际机场"
    },
    {
      "行程类型": "其他",
      "出发日期": "2026.9.17",
      "到达日期": "2026.9.17",
      "出发地": "西安",
      "到达地": "西安",
      "交通工具": "出租车/汽车/地铁",
      "发票类型": "增值税普通电子发票",
      "购买方名称": "中财汇通科技股份有限公司",
      "购买方统一社会信用代码/纳税人识别号": "91110000MA2234567Y",
      "销售方名称": "西安前进出租车有限公司",
      "销售方统一社会信用代码/纳税人识别号": "91610100MA0089012H",
      "发票号码": "DT7191103321142",
      "开票日期": "2026.9.17",
      "价税合计": "4.90",
      "税率": "3%",
      "税额": "0.14",
      "不含税金额": "4.76",
      "税目": "运输服务",
      "行程单ID": "DT20260917003",
      "行程金额": "4.90",
      "车型": "地铁",
      "行程人手机号": "13841587056",
      "行程时间": "2026-09-17 08:41至2026-09-17 09:14",
      "城市": "西安",
      "起点": "科技路站",
      "终点": "钟楼站"
    },
    {
      "行程类型": "飞机",
      "出发日期": "2026.9.19",
      "到达日期": "2026.9.19",
      "出发地": "西安",
      "到达地": "上海",
      "交通工具": "飞机",
      "座位等级": "经济舱",
      "时间": "17:08-19:31",
      "票价": "1404.00",
      "燃油附加费": "120.00",
      "增值税税率": "9%",
      "增值税税额": "145.26",
      "民航发展基金": "50.00",
      "其他税费": "40.00",
      "合计": "1614.00",
      "电子客票号": "4603257743247",
      "保险费": "30.00",
      "开票状态": "已开票",
      "发票号码": "CA1481020876426",
      "旅客": "梁梓涵",
      "购买方": "中财汇通科技股份有限公司",
      "出发": "西安咸阳国际机场",
      "到达": "上海虹桥国际机场",
      "线下预订审批描述": "",
      "实际支付金额": "1614.00"
    }
  ],
  "住宿明细": [
    {
      "入住日期": "2026.9.14",
      "退房日期": "2026.9.19",
      "酒店名称": "西安钟楼智选假日酒店",
      "所在位置": "西安市碑林区南大街8号",
      "住宿单价": "360.00",
      "住宿总额": "1800.00",
      "住宿人": "梁梓涵",
      "发票类型": "增值税普通电子发票",
      "购买方名称": "中财汇通科技股份有限公司",
      "购买方统一社会信用代码/纳税人识别号": "91110000MA2234567Y",
      "销售方名称": "西安钟楼智选假日酒店有限公司",
      "销售方统一社会信用代码/纳税人识别号": "9144030014337998A",
      "发票号码": "XS9627722631017",
      "开票日期": "2026.9.19",
      "价税合计": "1800.00",
      "税额": "101.89",
      "税率": "6%",
      "不含税金额": "1698.11",
      "税目": "住宿服务",
      "线下预订审批描述": "",
      "实际支付金额": "1800.00"
    }
  ],
  "费用分摊明细": [
    {
      "费用分摊主体": "产品管理部",
      "分摊比例": "50%",
      "报销金额": "2666.93"
    },
    {
      "费用分摊主体": "客户运营部",
      "分摊比例": "50%",
      "报销金额": "2666.93"
    }
  ],
  "资金支付信息": {
    "付款方式": "对私支付",
    "支付金额": "5333.86",
    "对私支付": "梁梓涵",
    "对公支付": ""
  }
}