{
  "单据编号": "101038",
  "业务类型": "差旅费报销",
  "公司": "中财汇通金融服务有限公司",
  "部门": "审计稽核部",
  "报销人": "姜春梅",
  "出差类型": "参加会议",
  "出发地": "深圳",
  "目的地": "成都",
  "途径城市": "无",
  "出差时间": "2026.10.23-2026.10.30",
  "费用分摊主体1": "审计稽核部",
  "费用分摊主体2": "市场销售部",
  "行程明细": [
    {
      "行程类型": "飞机",
      "出发日期": "2026.10.23",
      "到达日期": "2026.10.23",
      "出发地": "深圳",
      "到达地": "成都",
      "交通工具": "飞机",
      "座位等级": "经济舱",
      "时间": "10:38-13:57",
      "票价": "2638.00",
      "燃油附加费": "120.00",
      "增值税税率": "9%",
      "增值税税额": "255.42",
      "民航发展基金": "50.00",
      "其他税费": "30.00",
      "合计": "2838.00",
      "电子客票号": "9681976142783",
      "保险费": "30.00",
      "开票状态": "已开票",
      "发票号码": "CA8576747495950",
      "旅客": "姜春梅",
      "购买方": "中财汇通金融服务有限公司",
      "出发": "深圳宝安国际机场",
      "到达": "成都双流国际机场",
      "线下预订审批描述": "",
      "实际支付金额": "2838.00"
    },
    {
      "行程类型": "其他",
      "出发日期": "2026.10.23",
      "到达日期": "2026.10.23",
      "出发地": "成都",
      "到达地": "成都",
      "交通工具": "出租车/汽车/地铁",
      "发票类型": "增值税普通电子发票",
      "购买方名称": "中财汇通金融服务有限公司",
      "购买方统一社会信用代码/纳税人识别号": "91110000MA3234567Z",
      "销售方名称": "成都乘风出租车有限公司",
      "销售方统一社会信用代码/纳税人识别号": "91510100MA0056789E",
      "发票号码": "DT2563926917979",
      "开票日期": "2026.10.23",
      "价税合计": "64.90",
      "税率": "3%",
      "税额": "1.89",
      "不含税金额": "63.01",
      "税目": "运输服务",
      "行程单ID": "DT20261023000",
      "行程金额": "64.90",
      "车型": "出租车",
      "行程人手机号": "13820568669",
      "行程时间": "2026-10-23 10:14至2026-10-23 10:35",
      "城市": "成都",
      "起点": "成都双流国际机场",
      "终点": "成都市高新区天府大道北段1700号"
    },
    {
      "行程类型": "其他",
      "出发日期": "2026.10.25",
      "到达日期": "2026.10.25",
      "出发地": "成都",
      "到达地": "成都",
      "交通工具": "出租车/汽车/地铁",
      "发票类型": "增值税普通电子发票",
      "购买方名称": "中财汇通金融服务有限公司",
      "购买方统一社会信用代码/纳税人识别号": "91110000MA3234567Z",
      "销售方名称": "成都乘风出租车有限公司",
      "销售方统一社会信用代码/纳税人识别号": "91510100MA0056789E",
      "发票号码": "DT3979641334664",
      "开票日期": "2026.10.25",
      "价税合计": "84.57",
      "税率": "3%",
      "税额": "2.46",
      "不含税金额": "82.11",
      "税目": "运输服务",
      "行程单ID": "DT20261025002",
      "行程金额": "84.57",
      "车型": "出租车",
      "行程人手机号": "13834952431",
      "行程时间": "2026-10-25 20:57至2026-10-25 21:20",
      "城市": "成都",
      "起点": "成都东站",
      "终点": "成都市武侯区人民南路四段19号威斯顿联邦大厦"
    },
    {
      "行程类型": "其他",
      "出发日期": "2026.10.26",
      "到达日期": "2026.10.26",
      "出发地": "成都",
      "到达地": "成都",
      "交通工具": "出租车/汽车/地铁",
      "发票类型": "增值税普通电子发票",
      "购买方名称": "中财汇通金融服务有限公司",
      "购买方统一社会信用代码/纳税人识别号": "91110000MA3234567Z",
      "销售方名称": "成都乘风出租车有限公司",
      "销售方统一社会信用代码/纳税人识别号": "91510100MA0056789E",
      "发票号码": "DT4863810900382",
      "开票日期": "2026.10.26",
      "价税合计": "31.85",
      "税率": "3%",
      "税额": "0.93",
      "不含税金额": "30.92",
      "税目": "运输服务",
      "行程单ID": "DT20261026003",
      "行程金额": "31.85",
      "车型": "网约车",
      "行程人手机号": "13840954036",
      "行程时间": "2026-10-26 17:26至2026-10-26 18:06",
      "城市": "成都",
      "起点": "成都东站",
      "终点": "成都市高新区天府大道北段1700号"
    },
    {
      "行程类型": "其他",
      "出发日期": "2026.10.27",
      "到达日期": "2026.10.27",
      "出发地": "成都",
      "到达地": "成都",
      "交通工具": "出租车/汽车/地铁",
      "发票类型": "增值税普通电子发票",
      "购买方名称": "中财汇通金融服务有限公司",
      "购买方统一社会信用代码/纳税人识别号": "91110000MA3234567Z",
      "销售方名称": "成都乘风出租车有限公司",
      "销售方统一社会信用代码/纳税人识别号": "91510100MA0056789E",
      "发票号码": "DT2000739099857",
      "开票日期": "2026.10.27",
      "价税合计": "26.45",
      "税率": "3%",
      "税额": "0.77",
      "不含税金额": "25.68",
      "税目": "运输服务",
      "行程单ID": "DT20261027004",
      "行程金额": "26.45",
      "车型": "网约车",
      "行程人手机号": "13862616776",
      "行程时间": "2026-10-27 08:17至2026-10-27 09:11",
      "城市": "成都",
      "起点": "成都市锦江区东大街紫东楼段11号东方广场",
      "终点": "成都市武侯区人民南路四段19号威斯顿联邦大厦"
    },
    {
      "行程类型": "其他",
      "出发日期": "2026.10.29",
      "到达日期": "2026.10.29",
      "出发地": "成都",
      "到达地": "成都",
      "交通工具": "出租车/汽车/地铁",
      "发票类型": "增值税普通电子发票",
      "购买方名称": "中财汇通金融服务有限公司",
      "购买方统一社会信用代码/纳税人识别号": "91110000MA3234567Z",
      "销售方名称": "成都乘风出租车有限公司",
      "销售方统一社会信用代码/纳税人识别号": "91510100MA0056789E",
      "发票号码": "DT3758574792623",
      "开票日期": "2026.10.29",
      "价税合计": "72.73",
      "税率": "3%",
      "税额": "2.12",
      "不含税金额": "70.61",
      "税目": "运输服务",
      "行程单ID": "DT20261029006",
      "行程金额": "72.73",
      "车型": "网约车",
      "行程人手机号": "13853501419",
      "行程时间": "2026-10-29 21:58至2026-10-29 22:13",
      "城市": "成都",
      "起点": "成都市高新区天府大道北段1700号",
      "终点": "成都市武侯区人民南路四段19号威斯顿联邦大厦"
    },
    {
      "行程类型": "火车",
      "出发日期": "2026.10.30",
      "到达日期": "2026.10.30",
      "出发地": "成都",
      "到达地": "深圳",
      "交通工具": "火车",
      "发票号码": "T7883256666209",
      "开票日期": "2026.10.29",
      "席位号": "03车08F号",
      "车次": "G290",
      "时间": "07:15-14:30",
      "票价": "861.00",
      "座位等级": "二等座",
      "二维码": "4486019067705",
      "电子客票号": "4411164579738",
      "退票费": "0",
      "发站": "成都东站",
      "到站": "深圳北站",
      "乘车人": "姜春梅",
      "购买方名称": "中财汇通金融服务有限公司",
      "线下预订审批描述": "",
      "实际支付金额": "861.00"
    }
  ],
  "住宿明细": [
    {
      "入住日期": "2026.10.23",
      "退房日期": "2026.10.30",
      "酒店名称": "成都环球中心洲际酒店",
      "所在位置": "成都市高新区天府大道北段1700号",
      "住宿单价": "650.00",
      "住宿总额": "4550.00",
      "住宿人": "姜春梅",
      "发票类型": "增值税普通电子发票",
      "购买方名称": "中财汇通金融服务有限公司",
      "购买方统一社会信用代码/纳税人识别号": "91110000MA3234567Z",
      "销售方名称": "成都环球中心洲际酒店有限公司",
      "销售方统一社会信用代码/纳税人识别号": "9144030051001196A",
      "发票号码": "XS3985471838821",
      "开票日期": "2026.10.30",
      "价税合计": "4550.00",
      "税额": "257.55",
      "税率": "6%",
      "不含税金额": "4292.45",
      "税目": "住宿服务",
      "线下预订审批描述": "线下预订-住宿，入住时于酒店前台直接预订并支付，审批单号SP20260201",
      "实际支付金额": "4550.00"
    }
  ],
  "费用分摊明细": [
    {
      "费用分摊主体": "审计稽核部",
      "分摊比例": "50%",
      "报销金额": "4264.75"
    },
    {
      "费用分摊主体": "市场销售部",
      "分摊比例": "50%",
      "报销金额": "4264.75"
    }
  ],
  "资金支付信息": {
    "付款方式": "对私支付",
    "支付金额": "8529.50",
    "对私支付": "姜春梅",
    "对公支付": ""
  }
}