{
  "单据编号": "101146",
  "业务类型": "差旅费报销",
  "公司": "中财汇通金融服务有限公司",
  "部门": "市场销售部",
  "报销人": "侯春梅",
  "出差类型": "探亲出差",
  "出发地": "深圳",
  "目的地": "上海",
  "途径城市": "无",
  "出差时间": "2027.3.7-2027.3.15",
  "费用分摊主体1": "市场销售部",
  "费用分摊主体2": "无",
  "行程明细": [
    {
      "行程类型": "飞机",
      "出发日期": "2027.3.7",
      "到达日期": "2027.3.7",
      "出发地": "深圳",
      "到达地": "上海",
      "交通工具": "飞机",
      "座位等级": "经济舱",
      "时间": "08:20-11:53",
      "票价": "1706.00",
      "燃油附加费": "120.00",
      "增值税税率": "9%",
      "增值税税额": "168.84",
      "民航发展基金": "50.00",
      "其他税费": "0.00",
      "合计": "1876.00",
      "电子客票号": "6019303119970",
      "保险费": "30.00",
      "开票状态": "已开票",
      "发票号码": "CA7415636473238",
      "旅客": "侯春梅",
      "购买方": "中财汇通金融服务有限公司",
      "出发": "深圳宝安国际机场",
      "到达": "上海虹桥国际机场",
      "线下预订审批描述": "",
      "实际支付金额": "1876.00"
    },
    {
      "行程类型": "其他",
      "出发日期": "2027.3.8",
      "到达日期": "2027.3.8",
      "出发地": "上海",
      "到达地": "上海",
      "交通工具": "出租车/汽车/地铁",
      "发票类型": "增值税普通电子发票",
      "购买方名称": "中财汇通金融服务有限公司",
      "购买方统一社会信用代码/纳税人识别号": "91110000MA3234567Z",
      "销售方名称": "上海强生出租车有限公司",
      "销售方统一社会信用代码/纳税人识别号": "91310115MA0023456B",
      "发票号码": "DT3004567397615",
      "开票日期": "2027.3.8",
      "价税合计": "53.46",
      "税率": "3%",
      "税额": "1.56",
      "不含税金额": "51.90",
      "税目": "运输服务",
      "行程单ID": "DT20270308001",
      "行程金额": "53.46",
      "车型": "出租车",
      "行程人手机号": "13818616938",
      "行程时间": "2027-03-08 17:18至2027-03-08 18:07",
      "城市": "上海",
      "起点": "上海虹桥站",
      "终点": "上海虹桥国际机场"
    },
    {
      "行程类型": "其他",
      "出发日期": "2027.3.10",
      "到达日期": "2027.3.10",
      "出发地": "上海",
      "到达地": "上海",
      "交通工具": "出租车/汽车/地铁",
      "发票类型": "增值税普通电子发票",
      "购买方名称": "中财汇通金融服务有限公司",
      "购买方统一社会信用代码/纳税人识别号": "91110000MA3234567Z",
      "销售方名称": "上海强生出租车有限公司",
      "销售方统一社会信用代码/纳税人识别号": "91310115MA0023456B",
      "发票号码": "DT3608698179948",
      "开票日期": "2027.3.10",
      "价税合计": "71.96",
      "税率": "3%",
      "税额": "2.10",
      "不含税金额": "69.86",
      "税目": "运输服务",
      "行程单ID": "DT20270310003",
      "行程金额": "71.96",
      "车型": "出租车",
      "行程人手机号": "13884458076",
      "行程时间": "2027-03-10 16:23至2027-03-10 16:38",
      "城市": "上海",
      "起点": "上海虹桥站",
      "终点": "上海市浦东新区张江高科技园区博云路2号"
    },
    {
      "行程类型": "其他",
      "出发日期": "2027.3.12",
      "到达日期": "2027.3.12",
      "出发地": "上海",
      "到达地": "上海",
      "交通工具": "出租车/汽车/地铁",
      "发票类型": "增值税普通电子发票",
      "购买方名称": "中财汇通金融服务有限公司",
      "购买方统一社会信用代码/纳税人识别号": "91110000MA3234567Z",
      "销售方名称": "上海强生出租车有限公司",
      "销售方统一社会信用代码/纳税人识别号": "91310115MA0023456B",
      "发票号码": "DT8518293893340",
      "开票日期": "2027.3.12",
      "价税合计": "41.92",
      "税率": "3%",
      "税额": "1.22",
      "不含税金额": "40.70",
      "税目": "运输服务",
      "行程单ID": "DT20270312005",
      "行程金额": "41.92",
      "车型": "出租车",
      "行程人手机号": "13891755454",
      "行程时间": "2027-03-12 13:38至2027-03-12 14:24",
      "城市": "上海",
      "起点": "上海市闵行区申虹路333号",
      "终点": "上海市黄浦区南京东路228号"
    },
    {
      "行程类型": "其他",
      "出发日期": "2027.3.13",
      "到达日期": "2027.3.13",
      "出发地": "上海",
      "到达地": "上海",
      "交通工具": "出租车/汽车/地铁",
      "发票类型": "增值税普通电子发票",
      "购买方名称": "中财汇通金融服务有限公司",
      "购买方统一社会信用代码/纳税人识别号": "91110000MA3234567Z",
      "销售方名称": "上海强生出租车有限公司",
      "销售方统一社会信用代码/纳税人识别号": "91310115MA0023456B",
      "发票号码": "DT3724268949658",
      "开票日期": "2027.3.13",
      "价税合计": "82.89",
      "税率": "3%",
      "税额": "2.41",
      "不含税金额": "80.48",
      "税目": "运输服务",
      "行程单ID": "DT20270313006",
      "行程金额": "82.89",
      "车型": "出租车",
      "行程人手机号": "13886928718",
      "行程时间": "2027-03-13 06:22至2027-03-13 07:07",
      "城市": "上海",
      "起点": "上海市浦东新区张江碧波路888号",
      "终点": "上海市浦东新区张江高科技园区博云路2号"
    },
    {
      "行程类型": "其他",
      "出发日期": "2027.3.14",
      "到达日期": "2027.3.14",
      "出发地": "上海",
      "到达地": "上海",
      "交通工具": "出租车/汽车/地铁",
      "发票类型": "增值税普通电子发票",
      "购买方名称": "中财汇通金融服务有限公司",
      "购买方统一社会信用代码/纳税人识别号": "91110000MA3234567Z",
      "销售方名称": "上海强生出租车有限公司",
      "销售方统一社会信用代码/纳税人识别号": "91310115MA0023456B",
      "发票号码": "DT9524397301975",
      "开票日期": "2027.3.14",
      "价税合计": "43.25",
      "税率": "3%",
      "税额": "1.26",
      "不含税金额": "41.99",
      "税目": "运输服务",
      "行程单ID": "DT20270314007",
      "行程金额": "43.25",
      "车型": "网约车",
      "行程人手机号": "13822760708",
      "行程时间": "2027-03-14 12:14至2027-03-14 12:29",
      "城市": "上海",
      "起点": "上海市浦东新区张江高科技园区博云路2号",
      "终点": "上海市闵行区申虹路333号"
    },
    {
      "行程类型": "其他",
      "出发日期": "2027.3.15",
      "到达日期": "2027.3.15",
      "出发地": "上海",
      "到达地": "上海",
      "交通工具": "出租车/汽车/地铁",
      "发票类型": "增值税普通电子发票",
      "购买方名称": "中财汇通金融服务有限公司",
      "购买方统一社会信用代码/纳税人识别号": "91110000MA3234567Z",
      "销售方名称": "上海强生出租车有限公司",
      "销售方统一社会信用代码/纳税人识别号": "91310115MA0023456B",
      "发票号码": "DT8811504979946",
      "开票日期": "2027.3.15",
      "价税合计": "37.76",
      "税率": "3%",
      "税额": "1.10",
      "不含税金额": "36.66",
      "税目": "运输服务",
      "行程单ID": "DT20270315008",
      "行程金额": "37.76",
      "车型": "出租车",
      "行程人手机号": "13861198241",
      "行程时间": "2027-03-15 17:34至2027-03-15 18:20",
      "城市": "上海",
      "起点": "上海市徐汇区虹桥路1号港汇恒隆广场",
      "终点": "上海市闵行区申虹路333号"
    },
    {
      "行程类型": "飞机",
      "出发日期": "2027.3.15",
      "到达日期": "2027.3.15",
      "出发地": "上海",
      "到达地": "深圳",
      "交通工具": "飞机",
      "座位等级": "经济舱",
      "时间": "12:10-15:58",
      "票价": "2364.00",
      "燃油附加费": "120.00",
      "增值税税率": "9%",
      "增值税税额": "231.66",
      "民航发展基金": "50.00",
      "其他税费": "40.00",
      "合计": "2574.00",
      "电子客票号": "4335916799788",
      "保险费": "30.00",
      "开票状态": "已开票",
      "发票号码": "CA7901922999960",
      "旅客": "侯春梅",
      "购买方": "中财汇通金融服务有限公司",
      "出发": "上海虹桥国际机场",
      "到达": "深圳宝安国际机场",
      "线下预订审批描述": "",
      "实际支付金额": "2574.00"
    }
  ],
  "住宿明细": [
    {
      "入住日期": "2027.3.7",
      "退房日期": "2027.3.15",
      "酒店名称": "上海张江亚朵酒店",
      "所在位置": "上海市浦东新区张江碧波路888号",
      "住宿单价": "520.00",
      "住宿总额": "4160.00",
      "住宿人": "侯春梅",
      "发票类型": "增值税普通电子发票",
      "购买方名称": "中财汇通金融服务有限公司",
      "购买方统一社会信用代码/纳税人识别号": "91110000MA3234567Z",
      "销售方名称": "上海张江亚朵酒店有限公司",
      "销售方统一社会信用代码/纳税人识别号": "9144030071105286A",
      "发票号码": "XS4693126561612",
      "开票日期": "2027.3.15",
      "价税合计": "4160.00",
      "税额": "235.47",
      "税率": "6%",
      "不含税金额": "3924.53",
      "税目": "住宿服务",
      "线下预订审批描述": "",
      "实际支付金额": "4160.00"
    }
  ],
  "费用分摊明细": [
    {
      "费用分摊主体": "市场销售部",
      "分摊比例": "100%",
      "报销金额": "8941.24"
    }
  ],
  "资金支付信息": {
    "付款方式": "对公支付",
    "支付金额": "8941.24",
    "对私支付": "",
    "对公支付": "中财汇通金融服务有限公司"
  }
}