{
  "单据编号": "102004",
  "业务类型": "差旅费报销",
  "公司": "中财汇通科技股份有限公司",
  "部门": "安全合规部",
  "报销人": "汪超",
  "出差类型": "公务出差",
  "出发地": "上海",
  "目的地": "武汉",
  "途径城市": "无",
  "出差时间": "2027.6.17-2027.6.21",
  "费用分摊主体1": "安全合规部",
  "费用分摊主体2": "无",
  "行程明细": [
    {
      "行程类型": "飞机",
      "出发日期": "2027.6.17",
      "到达日期": "2027.6.17",
      "出发地": "上海",
      "到达地": "武汉",
      "交通工具": "飞机",
      "座位等级": "经济舱",
      "时间": "09:29-10:41",
      "票价": "2030.00",
      "燃油附加费": "50.00",
      "增值税税率": "9%",
      "增值税税额": "195.30",
      "民航发展基金": "50.00",
      "其他税费": "40.00",
      "合计": "2170.00",
      "电子客票号": "E2716753161",
      "保险费": "30.00",
      "开票状态": "已开票",
      "发票号码": "CA48795453",
      "旅客": "汪超",
      "购买方": "中财汇通科技股份有限公司",
      "出发": "上海虹桥国际机场",
      "到达": "武汉天河国际机场",
      "线下预订审批描述": "",
      "实际支付金额": "2170.00"
    },
    {
      "行程类型": "其他",
      "出发日期": "2027.6.19",
      "到达日期": "2027.6.19",
      "出发地": "武汉",
      "到达地": "武汉",
      "交通工具": "出租车/汽车/地铁",
      "发票类型": "增值税普通电子发票",
      "购买方名称": "中财汇通科技股份有限公司",
      "购买方统一社会信用代码/纳税人识别号": "91110000MA2234567Y",
      "销售方名称": "武汉大通出租车有限公司",
      "销售方统一社会信用代码/纳税人识别号": "91420100MA0056789E",
      "发票号码": "DT63774262",
      "开票日期": "2027.6.19",
      "价税合计": "4.69",
      "税率": "3%",
      "税额": "0.14",
      "不含税金额": "4.55",
      "税目": "运输服务",
      "行程单ID": "DT20270619002",
      "行程金额": "4.69",
      "车型": "地铁",
      "行程人手机号": "13880166740",
      "行程时间": "2027-06-19 19:36至2027-06-19 21:53",
      "城市": "武汉",
      "起点": "街道口站",
      "终点": "武汉商务区站"
    },
    {
      "行程类型": "其他",
      "出发日期": "2027.6.20",
      "到达日期": "2027.6.20",
      "出发地": "武汉",
      "到达地": "武汉",
      "交通工具": "出租车/汽车/地铁",
      "发票类型": "增值税普通电子发票",
      "购买方名称": "中财汇通科技股份有限公司",
      "购买方统一社会信用代码/纳税人识别号": "91110000MA2234567Y",
      "销售方名称": "武汉大通出租车有限公司",
      "销售方统一社会信用代码/纳税人识别号": "91420100MA0056789E",
      "发票号码": "DT24562649",
      "开票日期": "2027.6.20",
      "价税合计": "74.67",
      "税率": "3%",
      "税额": "2.17",
      "不含税金额": "72.50",
      "税目": "运输服务",
      "行程单ID": "DT20270620003",
      "行程金额": "74.67",
      "车型": "出租车",
      "行程人手机号": "13869540495",
      "行程时间": "2027-06-20 13:21至2027-06-20 15:09",
      "城市": "武汉",
      "起点": "武汉市洪山区关山大道589号",
      "终点": "武汉天河国际机场"
    },
    {
      "行程类型": "其他",
      "出发日期": "2027.6.21",
      "到达日期": "2027.6.21",
      "出发地": "武汉",
      "到达地": "武汉",
      "交通工具": "出租车/汽车/地铁",
      "发票类型": "增值税普通电子发票",
      "购买方名称": "中财汇通科技股份有限公司",
      "购买方统一社会信用代码/纳税人识别号": "91110000MA2234567Y",
      "销售方名称": "武汉大通出租车有限公司",
      "销售方统一社会信用代码/纳税人识别号": "91420100MA0056789E",
      "发票号码": "DT82864961",
      "开票日期": "2027.6.21",
      "价税合计": "6.48",
      "税率": "3%",
      "税额": "0.19",
      "不含税金额": "6.29",
      "税目": "运输服务",
      "行程单ID": "DT20270621004",
      "行程金额": "6.48",
      "车型": "地铁",
      "行程人手机号": "13898928020",
      "行程时间": "2027-06-21 15:02至2027-06-21 18:29",
      "城市": "武汉",
      "起点": "街道口站",
      "终点": "武汉商务区站"
    },
    {
      "行程类型": "火车",
      "出发日期": "2027.6.21",
      "到达日期": "2027.6.21",
      "出发地": "武汉",
      "到达地": "上海",
      "交通工具": "火车",
      "发票号码": "T89419191",
      "开票日期": "2027.6.20",
      "席位号": "06车13F号",
      "车次": "G3504",
      "时间": "16:59-18:32",
      "票价": "284.00",
      "座位等级": "二等座",
      "二维码": "E8964477361",
      "电子客票号": "E8926234885",
      "退票费": "0",
      "发站": "武汉站",
      "到站": "上海虹桥站",
      "乘车人": "汪超",
      "购买方名称": "中财汇通科技股份有限公司",
      "线下预订审批描述": "",
      "实际支付金额": "284.00"
    }
  ],
  "住宿明细": [
    {
      "入住日期": "2027.6.17",
      "退房日期": "2027.6.21",
      "酒店名称": "武汉东湖宾馆",
      "所在位置": "武汉市武昌区东湖路142号",
      "住宿单价": "550.00",
      "住宿总额": "2200.00",
      "住宿人": "汪超",
      "发票类型": "增值税专用电子发票",
      "购买方名称": "中财汇通科技股份有限公司",
      "购买方统一社会信用代码/纳税人识别号": "91110000MA2234567Y",
      "销售方名称": "武汉东湖宾馆有限公司",
      "销售方统一社会信用代码/纳税人识别号": "9144030096627862A",
      "发票号码": "XS99983634",
      "开票日期": "2027.6.21",
      "价税合计": "2200.00",
      "税额": "124.53",
      "税率": "6%",
      "不含税金额": "2075.47",
      "税目": "住宿服务",
      "线下预订审批描述": "",
      "实际支付金额": "2200.00"
    }
  ],
  "费用分摊明细": [
    {
      "费用分摊主体": "安全合规部",
      "分摊比例": "100%",
      "报销金额": "4739.84"
    }
  ],
  "资金支付信息": {
    "付款方式": "对私支付",
    "支付金额": "4739.84",
    "对私支付": "汪超",
    "对公支付": ""
  }
}