{
  "单据编号": "102265",
  "业务类型": "差旅费报销",
  "公司": "中财汇通金融服务有限公司",
  "部门": "风控合规部",
  "报销人": "乔红",
  "出差类型": "参加培训",
  "出发地": "深圳",
  "目的地": "武汉",
  "途径城市": "无",
  "出差时间": "2027.7.11-2027.7.18",
  "费用分摊主体1": "风控合规部",
  "费用分摊主体2": "无",
  "行程明细": [
    {
      "行程类型": "飞机",
      "出发日期": "2027.7.11",
      "到达日期": "2027.7.11",
      "出发地": "深圳",
      "到达地": "武汉",
      "交通工具": "飞机",
      "座位等级": "经济舱",
      "时间": "10:03-13:58",
      "票价": "1124.00",
      "燃油附加费": "150.00",
      "增值税税率": "9%",
      "增值税税额": "119.16",
      "民航发展基金": "50.00",
      "其他税费": "0.00",
      "合计": "1324.00",
      "电子客票号": "E6110553972",
      "保险费": "30.00",
      "开票状态": "已开票",
      "发票号码": "CA80416160",
      "旅客": "乔红",
      "购买方": "中财汇通金融服务有限公司",
      "出发": "深圳宝安国际机场",
      "到达": "武汉天河国际机场",
      "线下预订审批描述": "",
      "实际支付金额": "1324.00"
    },
    {
      "行程类型": "其他",
      "出发日期": "2027.7.13",
      "到达日期": "2027.7.13",
      "出发地": "武汉",
      "到达地": "武汉",
      "交通工具": "出租车/汽车/地铁",
      "发票类型": "增值税普通电子发票",
      "购买方名称": "中财汇通金融服务有限公司",
      "购买方统一社会信用代码/纳税人识别号": "91110000MA3234567Z",
      "销售方名称": "武汉大通出租车有限公司",
      "销售方统一社会信用代码/纳税人识别号": "91420100MA0056789E",
      "发票号码": "DT43256014",
      "开票日期": "2027.7.13",
      "价税合计": "61.99",
      "税率": "3%",
      "税额": "1.81",
      "不含税金额": "60.18",
      "税目": "运输服务",
      "行程单ID": "DT20270713002",
      "行程金额": "61.99",
      "车型": "出租车",
      "行程人手机号": "13814025729",
      "行程时间": "2027-07-13 13:16至2027-07-13 15:27",
      "城市": "武汉",
      "起点": "武汉站",
      "终点": "武汉市洪山区珞喻路1077号"
    },
    {
      "行程类型": "其他",
      "出发日期": "2027.7.14",
      "到达日期": "2027.7.14",
      "出发地": "武汉",
      "到达地": "武汉",
      "交通工具": "出租车/汽车/地铁",
      "发票类型": "增值税普通电子发票",
      "购买方名称": "中财汇通金融服务有限公司",
      "购买方统一社会信用代码/纳税人识别号": "91110000MA3234567Z",
      "销售方名称": "武汉大通出租车有限公司",
      "销售方统一社会信用代码/纳税人识别号": "91420100MA0056789E",
      "发票号码": "DT58912625",
      "开票日期": "2027.7.14",
      "价税合计": "3.01",
      "税率": "3%",
      "税额": "0.09",
      "不含税金额": "2.92",
      "税目": "运输服务",
      "行程单ID": "DT20270714003",
      "行程金额": "3.01",
      "车型": "地铁",
      "行程人手机号": "13832984844",
      "行程时间": "2027-07-14 17:33至2027-07-14 20:18",
      "城市": "武汉",
      "起点": "街道口站",
      "终点": "武汉商务区站"
    },
    {
      "行程类型": "其他",
      "出发日期": "2027.7.15",
      "到达日期": "2027.7.15",
      "出发地": "武汉",
      "到达地": "武汉",
      "交通工具": "出租车/汽车/地铁",
      "发票类型": "增值税普通电子发票",
      "购买方名称": "中财汇通金融服务有限公司",
      "购买方统一社会信用代码/纳税人识别号": "91110000MA3234567Z",
      "销售方名称": "武汉大通出租车有限公司",
      "销售方统一社会信用代码/纳税人识别号": "91420100MA0056789E",
      "发票号码": "DT36103245",
      "开票日期": "2027.7.15",
      "价税合计": "4.52",
      "税率": "3%",
      "税额": "0.13",
      "不含税金额": "4.39",
      "税目": "运输服务",
      "行程单ID": "DT20270715004",
      "行程金额": "4.52",
      "车型": "地铁",
      "行程人手机号": "13858195532",
      "行程时间": "2027-07-15 20:30至2027-07-15 22:58",
      "城市": "武汉",
      "起点": "光谷广场站",
      "终点": "循礼门站"
    },
    {
      "行程类型": "其他",
      "出发日期": "2027.7.16",
      "到达日期": "2027.7.16",
      "出发地": "武汉",
      "到达地": "武汉",
      "交通工具": "出租车/汽车/地铁",
      "发票类型": "增值税普通电子发票",
      "购买方名称": "中财汇通金融服务有限公司",
      "购买方统一社会信用代码/纳税人识别号": "91110000MA3234567Z",
      "销售方名称": "武汉大通出租车有限公司",
      "销售方统一社会信用代码/纳税人识别号": "91420100MA0056789E",
      "发票号码": "DT17906657",
      "开票日期": "2027.7.16",
      "价税合计": "26.84",
      "税率": "3%",
      "税额": "0.78",
      "不含税金额": "26.06",
      "税目": "运输服务",
      "行程单ID": "DT20270716005",
      "行程金额": "26.84",
      "车型": "出租车",
      "行程人手机号": "13887257797",
      "行程时间": "2027-07-16 10:42至2027-07-16 11:56",
      "城市": "武汉",
      "起点": "武汉天河国际机场",
      "终点": "武汉市洪山区关山大道589号"
    },
    {
      "行程类型": "其他",
      "出发日期": "2027.7.18",
      "到达日期": "2027.7.18",
      "出发地": "武汉",
      "到达地": "武汉",
      "交通工具": "出租车/汽车/地铁",
      "发票类型": "增值税普通电子发票",
      "购买方名称": "中财汇通金融服务有限公司",
      "购买方统一社会信用代码/纳税人识别号": "91110000MA3234567Z",
      "销售方名称": "武汉大通出租车有限公司",
      "销售方统一社会信用代码/纳税人识别号": "91420100MA0056789E",
      "发票号码": "DT20336653",
      "开票日期": "2027.7.18",
      "价税合计": "5.02",
      "税率": "3%",
      "税额": "0.15",
      "不含税金额": "4.87",
      "税目": "运输服务",
      "行程单ID": "DT20270718007",
      "行程金额": "5.02",
      "车型": "地铁",
      "行程人手机号": "13850633108",
      "行程时间": "2027-07-18 12:09至2027-07-18 14:23",
      "城市": "武汉",
      "起点": "光谷广场站",
      "终点": "循礼门站"
    },
    {
      "行程类型": "飞机",
      "出发日期": "2027.7.18",
      "到达日期": "2027.7.18",
      "出发地": "武汉",
      "到达地": "深圳",
      "交通工具": "飞机",
      "座位等级": "经济舱",
      "时间": "14:48-17:46",
      "票价": "1853.00",
      "燃油附加费": "150.00",
      "增值税税率": "9%",
      "增值税税额": "187.47",
      "民航发展基金": "50.00",
      "其他税费": "30.00",
      "合计": "2083.00",
      "电子客票号": "E8219356832",
      "保险费": "30.00",
      "开票状态": "已开票",
      "发票号码": "CA28028458",
      "旅客": "乔红",
      "购买方": "中财汇通金融服务有限公司",
      "出发": "武汉天河国际机场",
      "到达": "深圳宝安国际机场",
      "线下预订审批描述": "",
      "实际支付金额": "2083.00"
    }
  ],
  "住宿明细": [
    {
      "入住日期": "2027.7.11",
      "退房日期": "2027.7.18",
      "酒店名称": "武汉汉口泛海喜来登酒店",
      "所在位置": "武汉市江汉区范湖路80号",
      "住宿单价": "600.00",
      "住宿总额": "4200.00",
      "住宿人": "乔红",
      "发票类型": "增值税普通电子发票",
      "购买方名称": "中财汇通金融服务有限公司",
      "购买方统一社会信用代码/纳税人识别号": "91110000MA3234567Z",
      "销售方名称": "武汉汉口泛海喜来登酒店有限公司",
      "销售方统一社会信用代码/纳税人识别号": "9144030016598385A",
      "发票号码": "XS49578569",
      "开票日期": "2027.7.18",
      "价税合计": "4200.00",
      "税额": "237.74",
      "税率": "6%",
      "不含税金额": "3962.26",
      "税目": "住宿服务",
      "线下预订审批描述": "",
      "实际支付金额": "4200.00"
    }
  ],
  "费用分摊明细": [
    {
      "费用分摊主体": "风控合规部",
      "分摊比例": "100%",
      "报销金额": "7708.38"
    }
  ],
  "资金支付信息": {
    "付款方式": "对公支付",
    "支付金额": "7708.38",
    "对私支付": "",
    "对公支付": "中财汇通金融服务有限公司"
  }
}