{
  "单据编号": "102275",
  "业务类型": "差旅费报销",
  "公司": "中财汇通金融服务有限公司",
  "部门": "信息技术部",
  "报销人": "余涛",
  "出差类型": "公务出差",
  "出发地": "深圳",
  "目的地": "长沙",
  "途径城市": "无",
  "出差时间": "2027.2.14-2027.2.23",
  "费用分摊主体1": "信息技术部",
  "费用分摊主体2": "无",
  "行程明细": [
    {
      "行程类型": "飞机",
      "出发日期": "2027.2.14",
      "到达日期": "2027.2.14",
      "出发地": "深圳",
      "到达地": "长沙",
      "交通工具": "飞机",
      "座位等级": "经济舱",
      "时间": "07:07-09:14",
      "票价": "2053.00",
      "燃油附加费": "150.00",
      "增值税税率": "9%",
      "增值税税额": "202.77",
      "民航发展基金": "50.00",
      "其他税费": "0.00",
      "合计": "2253.00",
      "电子客票号": "E7243184770",
      "保险费": "30.00",
      "开票状态": "已开票",
      "发票号码": "CA53526255",
      "旅客": "余涛",
      "购买方": "中财汇通金融服务有限公司",
      "出发": "深圳宝安国际机场",
      "到达": "长沙黄花国际机场",
      "线下预订审批描述": "",
      "实际支付金额": "2253.00"
    },
    {
      "行程类型": "其他",
      "出发日期": "2027.2.15",
      "到达日期": "2027.2.15",
      "出发地": "长沙",
      "到达地": "长沙",
      "交通工具": "出租车/汽车/地铁",
      "发票类型": "增值税普通电子发票",
      "购买方名称": "中财汇通金融服务有限公司",
      "购买方统一社会信用代码/纳税人识别号": "91110000MA3234567Z",
      "销售方名称": "长沙蓝灯出租车有限公司",
      "销售方统一社会信用代码/纳税人识别号": "91430100MA0101234J",
      "发票号码": "DT77821596",
      "开票日期": "2027.2.15",
      "价税合计": "77.34",
      "税率": "3%",
      "税额": "2.25",
      "不含税金额": "75.09",
      "税目": "运输服务",
      "行程单ID": "DT20270215001",
      "行程金额": "77.34",
      "车型": "出租车",
      "行程人手机号": "13890815546",
      "行程时间": "2027-02-15 12:31至2027-02-15 14:59",
      "城市": "长沙",
      "起点": "长沙市天心区湘江中路二段36号",
      "终点": "长沙市雨花区万家丽中路三段189号"
    },
    {
      "行程类型": "其他",
      "出发日期": "2027.2.16",
      "到达日期": "2027.2.16",
      "出发地": "长沙",
      "到达地": "长沙",
      "交通工具": "出租车/汽车/地铁",
      "发票类型": "增值税普通电子发票",
      "购买方名称": "中财汇通金融服务有限公司",
      "购买方统一社会信用代码/纳税人识别号": "91110000MA3234567Z",
      "销售方名称": "长沙蓝灯出租车有限公司",
      "销售方统一社会信用代码/纳税人识别号": "91430100MA0101234J",
      "发票号码": "DT89988164",
      "开票日期": "2027.2.16",
      "价税合计": "7.11",
      "税率": "3%",
      "税额": "0.21",
      "不含税金额": "6.90",
      "税目": "运输服务",
      "行程单ID": "DT20270216002",
      "行程金额": "7.11",
      "车型": "地铁",
      "行程人手机号": "13841350060",
      "行程时间": "2027-02-16 14:40至2027-02-16 15:53",
      "城市": "长沙",
      "起点": "万家丽广场站",
      "终点": "梅溪湖西站"
    },
    {
      "行程类型": "其他",
      "出发日期": "2027.2.17",
      "到达日期": "2027.2.17",
      "出发地": "长沙",
      "到达地": "长沙",
      "交通工具": "出租车/汽车/地铁",
      "发票类型": "增值税普通电子发票",
      "购买方名称": "中财汇通金融服务有限公司",
      "购买方统一社会信用代码/纳税人识别号": "91110000MA3234567Z",
      "销售方名称": "长沙蓝灯出租车有限公司",
      "销售方统一社会信用代码/纳税人识别号": "91430100MA0101234J",
      "发票号码": "DT91792092",
      "开票日期": "2027.2.17",
      "价税合计": "83.39",
      "税率": "3%",
      "税额": "2.43",
      "不含税金额": "80.96",
      "税目": "运输服务",
      "行程单ID": "DT20270217003",
      "行程金额": "83.39",
      "车型": "网约车",
      "行程人手机号": "13816163728",
      "行程时间": "2027-02-17 18:05至2027-02-17 19:51",
      "城市": "长沙",
      "起点": "长沙市开福区湘江中路308号",
      "终点": "长沙南站"
    },
    {
      "行程类型": "其他",
      "出发日期": "2027.2.18",
      "到达日期": "2027.2.18",
      "出发地": "长沙",
      "到达地": "长沙",
      "交通工具": "出租车/汽车/地铁",
      "发票类型": "增值税普通电子发票",
      "购买方名称": "中财汇通金融服务有限公司",
      "购买方统一社会信用代码/纳税人识别号": "91110000MA3234567Z",
      "销售方名称": "长沙蓝灯出租车有限公司",
      "销售方统一社会信用代码/纳税人识别号": "91430100MA0101234J",
      "发票号码": "DT87351358",
      "开票日期": "2027.2.18",
      "价税合计": "3.89",
      "税率": "3%",
      "税额": "0.11",
      "不含税金额": "3.78",
      "税目": "运输服务",
      "行程单ID": "DT20270218004",
      "行程金额": "3.89",
      "车型": "地铁",
      "行程人手机号": "13831462402",
      "行程时间": "2027-02-18 20:26至2027-02-18 22:59",
      "城市": "长沙",
      "起点": "麓谷站",
      "终点": "五一广场站"
    },
    {
      "行程类型": "其他",
      "出发日期": "2027.2.19",
      "到达日期": "2027.2.19",
      "出发地": "长沙",
      "到达地": "长沙",
      "交通工具": "出租车/汽车/地铁",
      "发票类型": "增值税普通电子发票",
      "购买方名称": "中财汇通金融服务有限公司",
      "购买方统一社会信用代码/纳税人识别号": "91110000MA3234567Z",
      "销售方名称": "长沙蓝灯出租车有限公司",
      "销售方统一社会信用代码/纳税人识别号": "91430100MA0101234J",
      "发票号码": "DT69526847",
      "开票日期": "2027.2.19",
      "价税合计": "38.67",
      "税率": "3%",
      "税额": "1.13",
      "不含税金额": "37.54",
      "税目": "运输服务",
      "行程单ID": "DT20270219005",
      "行程金额": "38.67",
      "车型": "出租车",
      "行程人手机号": "13815526402",
      "行程时间": "2027-02-19 18:11至2027-02-19 20:50",
      "城市": "长沙",
      "起点": "长沙市岳麓区麓谷大道662号软件园",
      "终点": "长沙市开福区湘江中路308号"
    },
    {
      "行程类型": "其他",
      "出发日期": "2027.2.20",
      "到达日期": "2027.2.20",
      "出发地": "长沙",
      "到达地": "长沙",
      "交通工具": "出租车/汽车/地铁",
      "发票类型": "增值税普通电子发票",
      "购买方名称": "中财汇通金融服务有限公司",
      "购买方统一社会信用代码/纳税人识别号": "91110000MA3234567Z",
      "销售方名称": "长沙蓝灯出租车有限公司",
      "销售方统一社会信用代码/纳税人识别号": "91430100MA0101234J",
      "发票号码": "DT37031814",
      "开票日期": "2027.2.20",
      "价税合计": "77.98",
      "税率": "3%",
      "税额": "2.27",
      "不含税金额": "75.71",
      "税目": "运输服务",
      "行程单ID": "DT20270220006",
      "行程金额": "77.98",
      "车型": "网约车",
      "行程人手机号": "13861706259",
      "行程时间": "2027-02-20 06:09至2027-02-20 09:26",
      "城市": "长沙",
      "起点": "长沙黄花国际机场",
      "终点": "长沙市岳麓区麓谷大道662号软件园"
    },
    {
      "行程类型": "其他",
      "出发日期": "2027.2.23",
      "到达日期": "2027.2.23",
      "出发地": "长沙",
      "到达地": "长沙",
      "交通工具": "出租车/汽车/地铁",
      "发票类型": "增值税普通电子发票",
      "购买方名称": "中财汇通金融服务有限公司",
      "购买方统一社会信用代码/纳税人识别号": "91110000MA3234567Z",
      "销售方名称": "长沙蓝灯出租车有限公司",
      "销售方统一社会信用代码/纳税人识别号": "91430100MA0101234J",
      "发票号码": "DT70799272",
      "开票日期": "2027.2.23",
      "价税合计": "4.65",
      "税率": "3%",
      "税额": "0.14",
      "不含税金额": "4.51",
      "税目": "运输服务",
      "行程单ID": "DT20270223009",
      "行程金额": "4.65",
      "车型": "地铁",
      "行程人手机号": "13841271222",
      "行程时间": "2027-02-23 08:37至2027-02-23 09:53",
      "城市": "长沙",
      "起点": "麓谷站",
      "终点": "五一广场站"
    },
    {
      "行程类型": "飞机",
      "出发日期": "2027.2.23",
      "到达日期": "2027.2.23",
      "出发地": "长沙",
      "到达地": "深圳",
      "交通工具": "飞机",
      "座位等级": "经济舱",
      "时间": "10:07-12:33",
      "票价": "1801.00",
      "燃油附加费": "120.00",
      "增值税税率": "9%",
      "增值税税额": "180.09",
      "民航发展基金": "50.00",
      "其他税费": "30.00",
      "合计": "2001.00",
      "电子客票号": "E4515088106",
      "保险费": "30.00",
      "开票状态": "已开票",
      "发票号码": "CA81158104",
      "旅客": "余涛",
      "购买方": "中财汇通金融服务有限公司",
      "出发": "长沙黄花国际机场",
      "到达": "深圳宝安国际机场",
      "线下预订审批描述": "",
      "实际支付金额": "2001.00"
    }
  ],
  "住宿明细": [
    {
      "入住日期": "2027.2.14",
      "退房日期": "2027.2.23",
      "酒店名称": "长沙梅溪湖金茂豪华精选酒店",
      "所在位置": "长沙市岳麓区梅溪湖环湖路1177号",
      "住宿单价": "550.00",
      "住宿总额": "4950.00",
      "住宿人": "余涛",
      "发票类型": "增值税普通电子发票",
      "购买方名称": "中财汇通金融服务有限公司",
      "购买方统一社会信用代码/纳税人识别号": "91110000MA3234567Z",
      "销售方名称": "长沙梅溪湖金茂豪华精选酒店有限公司",
      "销售方统一社会信用代码/纳税人识别号": "9144030036357346A",
      "发票号码": "XS46602556",
      "开票日期": "2027.2.23",
      "价税合计": "4950.00",
      "税额": "280.19",
      "税率": "6%",
      "不含税金额": "4669.81",
      "税目": "住宿服务",
      "线下预订审批描述": "线下预订-住宿，入住时于酒店前台直接预订并支付，审批单号SP-20261025-864",
      "实际支付金额": "4950.00"
    }
  ],
  "费用分摊明细": [
    {
      "费用分摊主体": "信息技术部",
      "分摊比例": "100%",
      "报销金额": "9497.03"
    }
  ],
  "资金支付信息": {
    "付款方式": "对私支付",
    "支付金额": "9497.03",
    "对私支付": "余涛",
    "对公支付": ""
  }
}